olympic/__init__.py
olympic/callbacks.py
olympic/eval.py
olympic/layers.py
olympic/metrics.py
olympic/train.py
olympic-0.1.5.dist-info/LICENSE
olympic-0.1.5.dist-info/METADATA
olympic-0.1.5.dist-info/WHEEL
olympic-0.1.5.dist-info/top_level.txt
olympic-0.1.5.dist-info/RECORD
