Metadata-Version: 2.1
Name: olympic
Version: 0.1.5
Summary: A port of the Keras API to PyTorch
Home-page: http://github.com/oscarknagg/olympic-pytorch
Author: Oscar Knagg
Author-email: oscar@knagg.co.uk
License: MIT
Platform: UNKNOWN
Classifier: Programming Language :: Python :: 3.6
Classifier: License :: OSI Approved :: MIT License
Classifier: Operating System :: Unix
Requires-Dist: tqdm
Requires-Dist: torch
Requires-Dist: torchvision
